[
    {
      "nombre": "Ryoma Echizen",
      "equipo": "Seishun Gakuen (Seigaku)",
      "altura": "151 cm",
      "peso": "46 kg",
      "tecnica": "Twist Serve",
      "imagen": "https://e7.pngegg.com/pngimages/347/239/png-clipart-the-prince-of-tennis-sport-animation-tennis-sport-sports-equipment.png",
      "estiloJ": "All-rounder"
    },
    {
      "nombre": "Kunimitsu Tezuka",
      "equipo": "Seishun Gakuen (Seigaku)",
      "altura": "179 cm",
      "peso": "58 kg",
      "tecnica": "Tezuka Zone",
      "imagen": "https://example.com/tezuka.jpg",
      "estiloJ": "Controlador"
    },
    {
      "nombre": "Shuusuke Fuji",
      "equipo": "Seishun Gakuen (Seigaku)",
      "altura": "167 cm",
      "peso": "53 kg",
      "tecnica": "Tsubame Gaeshi",
      "imagen": "https://example.com/fuji.jpg",
      "estiloJ": "Contraataque"
    },
    {
      "nombre": "Sadaharu Inui",
      "equipo": "Seishun Gakuen (Seigaku)",
      "altura": "188 cm",
      "peso": "82 kg",
      "tecnica": "Data Tennis",
      "imagen": "https://example.com/inui.jpg",
      "estiloJ": "Estratégico"
    },
    {
      "nombre": "Eiji Kikumaru",
      "equipo": "Seishun Gakuen (Seigaku)",
      "altura": "171 cm",
      "peso": "52 kg",
      "tecnica": "Acrobatic Play",
      "imagen": "https://example.com/kikumaru.jpg",
      "estiloJ": "Velocidad"
    },
    {
      "nombre": "Takashi Kawamura",
      "equipo": "Seishun Gakuen (Seigaku)",
      "altura": "180 cm",
      "peso": "67 kg",
      "tecnica": "Burning Tennis",
      "imagen": "https://example.com/kawamura.jpg",
      "estiloJ": "Potencia"
    },
    {
      "nombre": "Syuichiro Oishi",
      "equipo": "Seishun Gakuen (Seigaku)",
      "altura": "175 cm",
      "peso": "55 kg",
      "tecnica": "Moon Volley",
      "imagen": "https://example.com/oishi.jpg",
      "estiloJ": "Dobles (especialista)"
    },
    {
      "nombre": "Kaoru Kaidoh",
      "equipo": "Seishun Gakuen (Seigaku)",
      "altura": "170 cm",
      "peso": "54 kg",
      "tecnica": "Boomerang Snake",
      "imagen": "https://example.com/kaidoh.jpg",
      "estiloJ": "Velocidad y resistencia"
    },
    {
      "nombre": "Takeshi Momoshiro",
      "equipo": "Seishun Gakuen (Seigaku)",
      "altura": "170 cm",
      "peso": "58 kg",
      "tecnica": "Dunk Smash",
      "imagen": "https://example.com/momoshiro.jpg",
      "estiloJ": "Potencia"
    },
    {
      "nombre": "Atobe Keigo",
      "equipo": "Hyotei Academy",
      "altura": "175 cm",
      "peso": "62 kg",
      "tecnica": "World of Ice",
      "imagen": "https://example.com/atobe.jpg",
      "estiloJ": "Controlador"
    },
    {
      "nombre": "Oshitari Yuushi",
      "equipo": "Hyotei Academy",
      "altura": "178 cm",
      "peso": "64 kg",
      "tecnica": "Illusion",
      "imagen": "https://example.com/oshitari.jpg",
      "estiloJ": "Estratégico"
    },
    {
      "nombre": "Mukahi Gakuto",
      "equipo": "Hyotei Academy",
      "altura": "160 cm",
      "peso": "50 kg",
      "tecnica": "Tightrope Walking",
      "imagen": "https://example.com/gakuto.jpg",
      "estiloJ": "Acrobático"
    },
    {
      "nombre": "Kabaji Munehiro",
      "equipo": "Hyotei Academy",
      "altura": "192 cm",
      "peso": "85 kg",
      "tecnica": "Copy",
      "imagen": "https://example.com/kabaji.jpg",
      "estiloJ": "Imitación"
    },
    {
      "nombre": "Sanada Genichirou",
      "equipo": "Rikkaidai Fuzoku",
      "altura": "180 cm",
      "peso": "68 kg",
      "tecnica": "Rai (Thunder)",
      "imagen": "https://example.com/sanada.jpg",
      "estiloJ": "Potencia y control"
    },
    {
      "nombre": "Yukimura Seiichi",
      "equipo": "Rikkaidai Fuzoku",
      "altura": "175 cm",
      "peso": "61 kg",
      "tecnica": "Yips",
      "imagen": "https://example.com/yukimura.jpg",
      "estiloJ": "Control mental"
    },
    {
      "nombre": "Kirihara Akaya",
      "equipo": "Rikkaidai Fuzoku",
      "altura": "168 cm",
      "peso": "57 kg",
      "tecnica": "Devil Mode",
      "imagen": "https://example.com/kirihara.jpg",
      "estiloJ": "Agresivo"
    },
    {
      "nombre": "Niou Masaharu",
      "equipo": "Rikkaidai Fuzoku",
      "altura": "175 cm",
      "peso": "62 kg",
      "tecnica": "Illusion",
      "imagen": "https://example.com/niou.jpg",
      "estiloJ": "Engaño"
    },
    {
      "nombre": "Yagyuu Hiroshi",
      "equipo": "Rikkaidai Fuzoku",
      "altura": "178 cm",
      "peso": "64 kg",
      "tecnica": "Laser Beam",
      "imagen": "https://example.com/yagyuu.jpg",
      "estiloJ": "Precisión"
    },
    {
      "nombre": "Shiraishi Kuranosuke",
      "equipo": "Shitenhouji",
      "altura": "179 cm",
      "peso": "67 kg",
      "tecnica": "Perfect Tennis",
      "imagen": "https://example.com/shiraishi.jpg",
      "estiloJ": "All-rounder"
    },
    {
      "nombre": "Kintarou Tooyama",
      "equipo": "Shitenhouji",
      "altura": "150 cm",
      "peso": "45 kg",
      "tecnica": "Super Shukuchihou",
      "imagen": "https://example.com/kintarou.jpg",
      "estiloJ": "Velocidad y potencia"
    },
    {
      "nombre": "Chitose Senri",
      "equipo": "Shitenhouji",
      "altura": "180 cm",
      "peso": "65 kg",
      "tecnica": "Hoshi Hanabi",
      "imagen": "https://example.com/chitose.jpg",
      "estiloJ": "Estratégico"
    },
    {
      "nombre": "Tachibana Kippei",
      "equipo": "Fudomine",
      "altura": "182 cm",
      "peso": "72 kg",
      "tecnica": "Abare Dama",
      "imagen": "https://example.com/tachibana.jpg",
      "estiloJ": "Potencia"
    },
    {
      "nombre": "Ibu Shinji",
      "equipo": "Fudomine",
      "altura": "165 cm",
      "peso": "55 kg",
      "tecnica": "Quick Serve",
      "imagen": "https://example.com/ibu.jpg",
      "estiloJ": "Velocidad"
    },
    {
      "nombre": "Akutsu Jin",
      "equipo": "Yamabuki",
      "altura": "185 cm",
      "peso": "75 kg",
      "tecnica": "Wild Tennis",
      "imagen": "https://example.com/akutsu.jpg",
      "estiloJ": "Agresivo"
    },
    {
      "nombre": "Minami Kentarou",
      "equipo": "Yamabuki",
      "altura": "170 cm",
      "peso": "60 kg",
      "tecnica": "Data Tennis",
      "imagen": "https://example.com/minami.jpg",
      "estiloJ": "Estratégico"
    },
    {
      "nombre": "Hiyoshi Wakashi",
      "equipo": "Hyotei Academy",
      "altura": "172 cm",
      "peso": "56 kg",
      "tecnica": "Bishop Step",
      "imagen": "https://example.com/hiyoshi.jpg",
      "estiloJ": "Velocidad"
    },
    {
      "nombre": "Shishido Ryou",
      "equipo": "Hyotei Academy",
      "altura": "174 cm",
      "peso": "60 kg",
      "tecnica": "Wild Ball",
      "imagen": "https://example.com/shishido.jpg",
      "estiloJ": "Agresivo"
    },
    {
      "nombre": "Jirou Akutagawa",
      "equipo": "Hyotei Academy",
      "altura": "160 cm",
      "peso": "52 kg",
      "tecnica": "Sleeping Mode",
      "imagen": "https://example.com/jirou.jpg",
      "estiloJ": "Impredecible"
    },
    {
      "nombre": "Zaizen Hikaru",
      "equipo": "Higa Chuu",
      "altura": "168 cm",
      "peso": "58 kg",
      "tecnica": "Hadoukyuu",
      "imagen": "https://example.com/zaizen.jpg",
      "estiloJ": "Potencia"
    }
]
